aftool/.DS_Store
aftool/__init__.py
aftool/cache.py
aftool/database.py
aftool/date.py
aftool/deep_learning.py
aftool/dynamic_graph.py
aftool/encrypt.py
aftool/fo.py
aftool/geno.py
aftool/help.py
aftool/jobs.py
aftool/log.py
aftool/simple_request.py
aftool/static_graph.py
aftool/tool.py
aftool-0.2.8.dist-info/LICENSE
aftool-0.2.8.dist-info/WHEEL
aftool-0.2.8.dist-info/METADATA
aftool-0.2.8.dist-info/RECORD
