Metadata-Version: 2.1
Name: aftool
Version: 0.2.8
Summary: Asdil Fibrizo's tool
Home-page: https://github.com/Asdil/aftool
License: MIT
Author: Asdil Fibrizo
Author-email: jpl4job@126.com
Requires-Python: >=3.6,<4.0
Classifier: License :: OSI Approved :: MIT License
Classifier: Programming Language :: Python :: 3
Classifier: Programming Language :: Python :: 3.6
Classifier: Programming Language :: Python :: 3.7
Classifier: Programming Language :: Python :: 3.8
Classifier: Programming Language :: Python :: 3.9
Requires-Dist: DBUtils (>=1.3,<2.0)
Requires-Dist: PyYAML (>=5.3.1,<6.0.0)
Requires-Dist: joblib (>=0.14.1,<0.15.0)
Requires-Dist: loguru (>=0.5.1,<0.6.0)
Requires-Dist: matplotlib (>=3.2.0,<4.0.0)
Requires-Dist: numpy (>=1.18.0,<2.0.0)
Requires-Dist: pandas (>=0.25.3,<0.26.0)
Requires-Dist: pip (>=20.0.2,<21.0.0)
Requires-Dist: plotly (>=4.9.0,<5.0.0)
Requires-Dist: psutil (>=5.6,<6.0)
Requires-Dist: pycryptodome (>=3.9.8,<4.0.0)
Requires-Dist: pyecharts (>=1.6.2,<2.0.0)
Requires-Dist: pymysql (>=0.10.0,<0.11.0)
Requires-Dist: pytest (>=5.3.5,<6.0.0)
Requires-Dist: python-dateutil (>=2.8.1,<3.0.0)
Requires-Dist: seaborn (>=0.10.0,<0.11.0)
Requires-Dist: snapshot_selenium (>=0.0.2,<0.0.3)
Requires-Dist: tqdm (>=4.41,<5.0)
Project-URL: Repository, https://github.com/Asdil/aftool
